drlogger/__init__.py
drlogger/formatter.py
drlogger/instrumentation.py
drlogger/main.py
drlogger-2.1.0.dist-info/LICENSE
drlogger-2.1.0.dist-info/METADATA
drlogger-2.1.0.dist-info/WHEEL
drlogger-2.1.0.dist-info/RECORD
