Metadata-Version: 2.1
Name: drlogger
Version: 2.1.0
Summary: 
Author: Ajamal Khan
Author-email: 13559558+khan-ajamal@users.noreply.github.com
Requires-Python: >=3.8,<4.0
Classifier: Programming Language :: Python :: 3
Classifier: Programming Language :: Python :: 3.8
Classifier: Programming Language :: Python :: 3.9
Classifier: Programming Language :: Python :: 3.10
Classifier: Programming Language :: Python :: 3.11
Classifier: Programming Language :: Python :: 3.12
Requires-Dist: graypy (>=2.1.0,<3.0.0)
Requires-Dist: python-json-logger (>=2.0.4,<3.0.0)
